git_remote_cvm/__init__.py
git_remote_cvm-1.15.dist-info/DESCRIPTION.rst
git_remote_cvm-1.15.dist-info/METADATA
git_remote_cvm-1.15.dist-info/RECORD
git_remote_cvm-1.15.dist-info/WHEEL
git_remote_cvm-1.15.dist-info/entry_points.txt
git_remote_cvm-1.15.dist-info/metadata.json
git_remote_cvm-1.15.dist-info/top_level.txt
