Metadata-Version: 2.0
Name: git-remote-cvm
Version: 1.15
Summary: Git remote prefix to simplify pushing to and pulling from CodeCommit using the CVM.
Home-page: https://github.com/jcaxmacher/git-remote-cvm
Author: Amazon Web Services and Jeremy Axmacher
Author-email: UNKNOWN
License: Apache License 2.0
Platform: UNKNOWN
Classifier: Development Status :: 4 - Beta
Classifier: Intended Audience :: Developers
Classifier: Topic :: Utilities
Classifier: License :: OSI Approved :: Apache Software License
Requires-Dist: botocore (>=1.10.4)
